cloudflare_encrypt-0.1.0.dist-info/METADATA
cloudflare_encrypt-0.1.0.dist-info/WHEEL
cloudflare_encrypt-0.1.0.dist-info/licenses/LICENSE
cloudflare_encrypt/__init__.py
cloudflare_encrypt/cloudflare_encrypt.cpython-311-darwin.so
cloudflare_encrypt-0.1.0.dist-info/RECORD
