Metadata-Version: 2.4
Name: cloudflare_encrypt
Version: 0.1.0
Classifier: Programming Language :: Python :: 3
Classifier: License :: OSI Approved :: MIT License
Classifier: Operating System :: OS Independent
License-File: LICENSE
Summary: cloudflare_encrypt package
Keywords: pyo3,rust,python
Author-email: Your Name <www@gmail.com>
Requires-Python: >=3.8
